btclib/__init__.py
btclib/alias.py
btclib/amount.py
btclib/b32.py
btclib/b58.py
btclib/base58.py
btclib/bech32.py
btclib/descriptors.py
btclib/exceptions.py
btclib/hashes.py
btclib/network.py
btclib/number_theory.py
btclib/py.typed
btclib/to_prv_key.py
btclib/to_pub_key.py
btclib/utils.py
btclib/var_bytes.py
btclib/var_int.py
btclib/_data/mainnet.json
btclib/_data/regtest.json
btclib/_data/testnet.json
btclib/bip32/__init__.py
btclib/bip32/bip32.py
btclib/bip32/der_path.py
btclib/bip32/key_origin.py
btclib/bip32/slip132.py
btclib/block/__init__.py
btclib/block/block.py
btclib/block/block_header.py
btclib/ec/__init__.py
btclib/ec/curve.py
btclib/ec/curve_group.py
btclib/ec/curve_group_2.py
btclib/ec/curve_group_f.py
btclib/ec/libsecp256k1.py
btclib/ec/sec_point.py
btclib/ec/_data/ec_Brainpool.json
btclib/ec/_data/ec_NIST.json
btclib/ec/_data/ec_SEC2v1_insecure.json
btclib/ec/_data/ec_SEC2v2.json
btclib/ecc/__init__.py
btclib/ecc/bip340_nonce.py
btclib/ecc/bms.py
btclib/ecc/borromean.py
btclib/ecc/dh.py
btclib/ecc/dsa.py
btclib/ecc/libsecp256k1.py
btclib/ecc/pedersen.py
btclib/ecc/rfc6979_nonce.py
btclib/ecc/sign_to_contract.py
btclib/ecc/ssa.py
btclib/mnemonic/__init__.py
btclib/mnemonic/bip39.py
btclib/mnemonic/electrum.py
btclib/mnemonic/entropy.py
btclib/mnemonic/mnemonic.py
btclib/mnemonic/_data/english.txt
btclib/mnemonic/_data/italian.txt
btclib/psbt/__init__.py
btclib/psbt/psbt.py
btclib/psbt/psbt_in.py
btclib/psbt/psbt_out.py
btclib/psbt/psbt_utils.py
btclib/script/__init__.py
btclib/script/op_codes_tapscript.py
btclib/script/script.py
btclib/script/script_pub_key.py
btclib/script/sig_hash.py
btclib/script/taproot.py
btclib/script/witness.py
btclib/script/engine/__init__.py
btclib/script/engine/script.py
btclib/script/engine/script_op_codes.py
btclib/script/engine/tapscript.py
btclib/tx/__init__.py
btclib/tx/out_point.py
btclib/tx/tx.py
btclib/tx/tx_in.py
btclib/tx/tx_out.py
docs/Makefile
docs/README.rst
docs/make.bat
docs/requirements.txt
btclib-2023.7.12.dist-info/AUTHORS.md
btclib-2023.7.12.dist-info/LICENSE
btclib-2023.7.12.dist-info/METADATA
btclib-2023.7.12.dist-info/WHEEL
btclib-2023.7.12.dist-info/top_level.txt
btclib-2023.7.12.dist-info/RECORD
