Metadata-Version: 2.1
Name: btclib
Version: 2023.7.12
Summary: A library for 'bitcoin cryptography'
Home-page: https://btclib.org
Author: The btclib developers
Author-email: devs@btclib.org
License: MIT License
Project-URL: Download, https://github.com/btclib-org/btclib/releases
Project-URL: Documentation, https://btclib.readthedocs.io/
Project-URL: GitHub, https://github.com/btclib-org/btclib
Project-URL: Issues, https://github.com/btclib-org/btclib/issues
Project-URL: Pull Requests, https://github.com/btclib-org/btclib/pulls
Keywords: bitcoin cryptography elliptic-curves ecdsa schnorr RFC-6979 bip32 bip39 electrum base58 bech32 segwit message-signing bip340
Classifier: Programming Language :: Python :: 3 :: Only
Classifier: Programming Language :: Python :: 3
Classifier: Programming Language :: Python :: 3.7
Classifier: Programming Language :: Python :: 3.8
Classifier: Programming Language :: Python :: 3.9
Classifier: Programming Language :: Python :: 3.10
Classifier: Programming Language :: Python :: 3.11
Classifier: Programming Language :: Python :: 3.12
Classifier: Programming Language :: Python :: Implementation :: CPython
Classifier: Programming Language :: Python :: Implementation :: PyPy
Classifier: Development Status :: 4 - Beta
Classifier: Intended Audience :: Developers
Classifier: Intended Audience :: Education
Classifier: License :: OSI Approved :: MIT License
Classifier: Natural Language :: English
Classifier: Operating System :: OS Independent
Classifier: Topic :: Scientific/Engineering
Classifier: Topic :: Security :: Cryptography
Classifier: Topic :: Software Development :: Libraries :: Python Modules
Classifier: Typing :: Typed
Requires-Python: >=3.7
License-File: LICENSE
License-File: AUTHORS.md
